{ "name": "channel_3d_smooth_rcParNew98",
  "template" : "channel_3d_smooth_rcPar2_template",
  "epsType": "smooth",
  "submit" : "yes",
  "decompose" : "no",
  "serialRun" : "yes",
  "sampleTime" : 60, 
  "vectorSample" : ["y","Ux","Uy","Uz","tppsiX","tppsiY","tppsiZ","vorticityX","vorticityY","vorticityZ"],
  "scalarSample" : ["y", "p", "k", "epsilon", "tpphi", "nut","epsHat","tpProd"],
  "dataTypes" : ["num","num","num"],
  "data": {
    "constant1" : [1.83, 1.88, 1.92],
    "constant2"	: [0.83, 1.0, 1.2],
    "constant3" : [0.33, 0.4, 0.5]  
  },
  "notes" : "New Elliptic version 2"
}

